README.md
sciplot/__init__.py
sciplot/main.py
sciplot/parameters/alpha.yml
sciplot/parameters/basic.yml
sciplot/parameters/beta.yml
sciplot/parameters/colors.yml
sciplot/parameters/colors_dark.yml
sciplot/parameters/colors_light.yml
sciplot/parameters/fonts_cm_sans_serif.yml
sciplot/parameters/fonts_cm_serif.yml
sciplot/parameters/fonts_sans_serif.yml
sciplot/parameters/fonts_serif.yml
sciplot/parameters/gamma.yml
sciplot/parameters/latex_sans_serif.yml
sciplot/parameters/latex_serif.yml
sciplot/parameters/no_latex.yml
sciplot/parameters/typesetting.yml
sciplot-0.8.1.dist-info/LICENSE.txt
sciplot-0.8.1.dist-info/METADATA
sciplot-0.8.1.dist-info/WHEEL
sciplot-0.8.1.dist-info/top_level.txt
sciplot-0.8.1.dist-info/RECORD
